nuanced_mcp_server.py
mseep_nuanced_mcp-0.1.4.dist-info/METADATA
mseep_nuanced_mcp-0.1.4.dist-info/WHEEL
mseep_nuanced_mcp-0.1.4.dist-info/top_level.txt
mseep_nuanced_mcp-0.1.4.dist-info/RECORD
