Metadata-Version: 2.4
Name: mseep-nuanced-mcp
Version: 0.1.4
Summary: MCP server expose nuanced.dev functionality
Author-email: mseep <support@skydeck.ai>
Requires-Python: >=3.13
Requires-Dist: mcp[cli]>=1.3.0
Requires-Dist: nuanced>=0.1.4
